duckducksearch/__init__.py
duckducksearch/duckducksearch.py
duckducksearch-0.1.0.dist-info/LICENSE
duckducksearch-0.1.0.dist-info/METADATA
duckducksearch-0.1.0.dist-info/WHEEL
duckducksearch-0.1.0.dist-info/top_level.txt
duckducksearch-0.1.0.dist-info/RECORD
