Metadata-Version: 2.1
Name: duckducksearch
Version: 0.1.0
Summary: A Python library for searching using DuckDuckGo.
Home-page: https://github.com/bes-dev/duckducksearch
Author: Sergei Belousov aka bes-dev
Author-email: sergei.o.belousov@gmail.com
License: UNKNOWN
Platform: UNKNOWN
Classifier: Programming Language :: Python :: 3
Classifier: License :: OSI Approved :: Apache Software License
Classifier: Operating System :: OS Independent
Requires-Python: >=3.7
License-File: LICENSE
Requires-Dist: duckduckgo-search>=7.3.0
